{
  "ExercisesByMuscleGroups":[
    {
      "name": "Neck",
      "href": "https://exrx.net/Lists/ExList/NeckWt",
      "muscles": {
        "Sternocleidomastoid": {
          "Cable": [
            {
              "name": "Neck Flexion",
              "href": "https://exrx.net/WeightExercises/Sternocleidomastoid/CBNeckFlx"
            },
            {
              "name": "Neck Rotation (with belt)",
              "href": "https://exrx.net/WeightExercises/Sternocleidomastoid/CBNeckRotationBelt"
            },
            {
              "name": "Lateral Neck Flexion (with belt)",
              "href": "https://exrx.net/WeightExercises/Sternocleidomastoid/CBNeckLtrFlxBelt"
            }
          ],
          "Lever (plate loaded)": [
            {
              "name": "Neck Flexion",
              "href": "https://exrx.net/WeightExercises/Sternocleidomastoid/LVNeckFlexionH"
            },
            {
              "name": "Lateral Neck Flexion",
              "href": "https://exrx.net/WeightExercises/Sternocleidomastoid/LVLateralNeckFlexionH"
            }
          ],
          "Lever (selectorized)": [
            {
              "name": "Neck Flexion",
              "href": "https://exrx.net/WeightExercises/Sternocleidomastoid/LVNeckFlx"
            },
            {
              "name": "Lateral Neck Flexion",
              "href": "https://exrx.net/WeightExercises/Sternocleidomastoid/LVNeckLtrFlx"
            }
          ],
          "Weighted": [
            {
              "name": "Lying Neck Flexion",
              "href": "https://exrx.net/WeightExercises/Sternocleidomastoid/WtLyingNeckFlexion"
            },
            {
              "name": "Neck Flexion",
              "href": "https://exrx.net/WeightExercises/Sternocleidomastoid/WtNeckFlx"
            },
            {
              "name": "Lateral Neck Flexion",
              "href": "https://exrx.net/WeightExercises/Sternocleidomastoid/WtNeckLateralFlex"
            }
          ],
          "Body Weight": [
            {
              "name": "Front Neck Bridge",
              "href": "https://exrx.net/WeightExercises/Sternocleidomastoid/BWFrontNeckBridge"
            },
            {
              "name": "Wall Front Neck Bridge",
              "href": "https://exrx.net/WeightExercises/Sternocleidomastoid/BWWallFrontNeckBridge"
            },
            {
              "name": "Wall Side Neck Bridge",
              "href": "https://exrx.net/WeightExercises/Sternocleidomastoid/BWWallSideNeckBridge"
            }
          ],
          "Stretch": [
            {
              "name": "Retraction",
              "href": "https://exrx.net/Stretches/Sternocleidomastoid/NeckRetraction"
            },
            {
              "name": "Rotation",
              "href": "https://exrx.net/Stretches/Sternocleidomastoid/NeckRotation"
            }
          ],
          "Suspended": [
            {
              "name": "Neck Flexion",
              "href": "https://exrx.net/WeightExercises/Sternocleidomastoid/STNeckFlexion"
            },
            { "name": "Lateral Neck Flexion", "href": null }
          ]
        },
        "Splenius": {
          "Cable": [
            {
              "name": "Neck Extension",
              "href": "https://exrx.net/WeightExercises/Splenius/CBNeckExt"
            }
          ],
          "Lever (plate loaded)": [
            {
              "name": "Neck Extension",
              "href": "https://exrx.net/WeightExercises/Splenius/LVNeckExtentionH"
            }
          ],
          "Lever (selectorized)": [
            {
              "name": "Neck Extension",
              "href": "https://exrx.net/WeightExercises/Splenius/LVNeckExt"
            }
          ],
          "Weighted": [
            {
              "name": "Lying Neck Extension",
              "href": "https://exrx.net/WeightExercises/Splenius/WtLyingNeckExtension"
            },
            {
              "name": "Neck Extension",
              "href": "https://exrx.net/WeightExercises/Splenius/WtNeckExtension"
            },
            {
              "name": "Seated Neck Extension",
              "href": "https://exrx.net/WeightExercises/Splenius/WtNeckExt"
            }
          ],
          "Band Resistive": [{ "name": "Neck Retraction", "href": null }],
          "Body Weight": [
            {
              "name": "Rear Neck Bridge",
              "href": "https://exrx.net/WeightExercises/Splenius/BWRearNeckBridge"
            },
            {
              "name": "Wall Rear Neck Bridge",
              "href": "https://exrx.net/WeightExercises/Splenius/BWWallRearNeckBridge"
            }
          ],
          "Isometric": [{ "name": "Lying Neck Retraction", "href": null }],
          "Stretch": [
            {
              "name": "Neck Extensor",
              "href": "https://exrx.net/Stretches/Splenius/Neck"
            }
          ],
          "Suspended": [
            {
              "name": "Neck Extension",
              "href": "https://exrx.net/WeightExercises/Splenius/STNeckExtension"
            }
          ]
        }
      }
    },
    {
      "name": "Shoulders",
      "href": "https://exrx.net/Lists/ExList/ShouldWt",
      "muscles": {
        "Anterior Deltoid": {
          "Barbell": [
            {
              "name": "Behind Neck Press",
              "href": "https://exrx.net/WeightExercises/DeltoidAnterior/BBBehindNeckPress"
            },
            {
              "name": "Front Raise",
              "href": "https://exrx.net/WeightExercises/DeltoidAnterior/BBFrontRaise"
            },
            {
              "name": "Military Press",
              "href": "https://exrx.net/WeightExercises/DeltoidAnterior/BBMilitaryPress"
            },
            { "name": "Shoulder Press", "href": null }
          ],
          "Cable": [
            { "name": "Cable Bar", "href": null },
            {
              "name": "Front Raise",
              "href": "https://exrx.net/WeightExercises/DeltoidAnterior/CBSeatedFrontRaise"
            },
            {
              "name": "Shoulder Press",
              "href": "https://exrx.net/WeightExercises/DeltoidAnterior/CBStandingShoulderPress"
            },
            {
              "name": "Twisting Overhead Press",
              "href": "https://exrx.net/WeightExercises/DeltoidAnterior/CBTwistingOverheadPress"
            }
          ],
          "Dumbbell": [
            {
              "name": "Arnold Press",
              "href": "https://exrx.net/WeightExercises/DeltoidAnterior/DBArnoldPress"
            },
            {
              "name": "Front Raise",
              "href": "https://exrx.net/WeightExercises/DeltoidAnterior/DBFrontRaise"
            },
            {
              "name": "Shoulder Press",
              "href": "https://exrx.net/WeightExercises/DeltoidAnterior/DBShoulderPress"
            }
          ],
          "Lever (plate loaded)": [
            {
              "name": "Behind Neck Press",
              "href": "https://exrx.net/WeightExercises/DeltoidAnterior/LVBehindNeckPressH"
            },
            {
              "name": "Military Press",
              "href": "https://exrx.net/WeightExercises/DeltoidAnterior/LVMilitaryPressH"
            },
            {
              "name": "Reclined Shoulder Press",
              "href": "https://exrx.net/WeightExercises/DeltoidAnterior/LVReclinedShoulderPressPL"
            },
            {
              "name": "Shoulder Press",
              "href": "https://exrx.net/WeightExercises/DeltoidAnterior/LVShoulderPressH"
            }
          ],
          "Lever (selectorized)": [
            {
              "name": "Front Raise",
              "href": "https://exrx.net/WeightExercises/DeltoidAnterior/LVFrontRaise"
            },
            {
              "name": "Reclined Shoulder Press",
              "href": "https://exrx.net/WeightExercises/DeltoidAnterior/LVReclinedShoulderPress"
            },
            {
              "name": "Shoulder Press",
              "href": "https://exrx.net/WeightExercises/DeltoidAnterior/LVShoulderPress"
            }
          ],
          "Sled": [
            {
              "name": "Shoulder Press",
              "href": "https://exrx.net/WeightExercises/DeltoidAnterior/SLShoulderPress"
            }
          ],
          "Smith": [
            {
              "name": "Behind Neck Press",
              "href": "https://exrx.net/WeightExercises/DeltoidAnterior/SMBehindNeckPress"
            },
            {
              "name": "Shoulder Press",
              "href": "https://exrx.net/WeightExercises/DeltoidAnterior/SMShoulderPress"
            }
          ],
          "Body Weight": [
            { "name": "Handstand Push-up", "href": null },
            { "name": "Pike Press", "href": null }
          ],
          "Suspended": [
            {
              "name": "Front Raise",
              "href": "https://exrx.net/WeightExercises/DeltoidAnterior/STFrontRaise"
            }
          ],
          "Stretch": [
            {
              "name": "Doorway",
              "href": "https://exrx.net/Stretches/DeltoidAnterior/Doorway"
            },
            {
              "name": "Lying Front Deltoid Stretch",
              "href": "https://exrx.net/Stretches/DeltoidAnterior/Lying"
            },
            {
              "name": "Seated Front Deltoid Stretch",
              "href": "https://exrx.net/Stretches/DeltoidAnterior/Seated"
            },
            {
              "name": "Wall",
              "href": "https://exrx.net/Stretches/DeltoidAnterior/Wall"
            }
          ]
        },
        "Lateral Deltoid": {
          "Barbell": [{ "name": "Upright Row", "href": null }],
          "Cable": [
            {
              "name": "Lateral Raise",
              "href": "https://exrx.net/WeightExercises/DeltoidLateral/CBLateralRaise"
            },
            {
              "name": "Upright Row",
              "href": "https://exrx.net/WeightExercises/DeltoidLateral/CBUprightRow"
            },
            {
              "name": "Y Raise",
              "href": "https://exrx.net/WeightExercises/DeltoidLateral/CBYRaise"
            }
          ],
          "Dumbbell": [
            {
              "name": "Incline Lateral Raise",
              "href": "https://exrx.net/WeightExercises/DeltoidLateral/DBInclineLateralRaise"
            },
            {
              "name": "Lateral Raise",
              "href": "https://exrx.net/WeightExercises/DeltoidLateral/DBLateralRaise"
            },
            {
              "name": "Lying Lateral Raise",
              "href": "https://exrx.net/WeightExercises/DeltoidLateral/DBLyingLateralRaise"
            },
            { "name": "Raise", "href": null },
            {
              "name": "Upright Row",
              "href": "https://exrx.net/WeightExercises/DeltoidLateral/DBUprightRow"
            }
          ],
          "Lever (plate loaded)": [
            {
              "name": "Barbell Machine Upright Row",
              "href": "https://exrx.net/WeightExercises/DeltoidLateral/LVBBUprightRow"
            },
            {
              "name": "Lateral Raise",
              "href": "https://exrx.net/WeightExercises/DeltoidLateral/LVLateralRaiseH"
            }
          ],
          "Lever (selectorized)": [
            {
              "name": "Lateral Raise",
              "href": "https://exrx.net/WeightExercises/DeltoidLateral/LVLateralRaise"
            }
          ],
          "Smith": [{ "name": "Upright Row", "href": null }],
          "Stretch": [
            {
              "name": "Fixed Bar",
              "href": "https://exrx.net/Stretches/DeltoidLateral/FixedBar"
            },
            {
              "name": "Side Deltoid",
              "href": "https://exrx.net/Stretches/DeltoidLateral/SideDelt"
            }
          ],
          "Suspended": [
            {
              "name": "Y Raise",
              "href": "https://exrx.net/WeightExercises/DeltoidLateral/STYShoulderRaise"
            }
          ]
        },
        "Posterior Deltoid": {
          "Barbell": [
            {
              "name": "Rear Delt Raise",
              "href": "https://exrx.net/WeightExercises/DeltoidPosterior/BBRearDeltRaise"
            },
            {
              "name": "Rear Delt Row",
              "href": "https://exrx.net/WeightExercises/DeltoidPosterior/BBRearDeltRow"
            },
            {
              "name": "Lying Rear Delt Row",
              "href": "https://exrx.net/WeightExercises/DeltoidPosterior/BBLyingRearDeltRow"
            }
          ],
          "Cable": [
            {
              "name": "Reverse Fly",
              "href": "https://exrx.net/WeightExercises/DeltoidPosterior/CBStandingReverseFly"
            },
            {
              "name": "Rear Delt Row",
              "href": "https://exrx.net/WeightExercises/DeltoidPosterior/CBRearDeltRow"
            },
            {
              "name": "Rear Lateral Raise",
              "href": "https://exrx.net/WeightExercises/DeltoidPosterior/CBRearLateralRaise"
            },
            {
              "name": "Standing Cross Row",
              "href": "https://exrx.net/WeightExercises/DeltoidPosterior/CBStandingCrossRow"
            }
          ],
          "Dumbbell": [
            {
              "name": "Lying Rear Delt Row",
              "href": "https://exrx.net/WeightExercises/DeltoidPosterior/DBLyingRearDeltRow"
            },
            {
              "name": "Lying Rear Lateral Raise",
              "href": "https://exrx.net/WeightExercises/DeltoidPosterior/DBLyingRearLateralRaise"
            },
            {
              "name": "Rear Lateral Raise",
              "href": "https://exrx.net/WeightExercises/DeltoidPosterior/DBRearLateralRaise"
            },
            {
              "name": "Rear Delt Row",
              "href": "https://exrx.net/WeightExercises/DeltoidPosterior/DBRearDeltRow"
            },
            {
              "name": "Seated Rear Lateral Raise",
              "href": "https://exrx.net/WeightExercises/DeltoidPosterior/DBSeatedRearLateralRaise"
            },
            { "name": "Side Lying Rear Delt Raise", "href": null }
          ],
          "Lever (plate loaded)": [
            {
              "name": "Incline Rear Delt Row",
              "href": "https://exrx.net/WeightExercises/DeltoidPosterior/LVInclineRearDeltRowPL"
            },
            {
              "name": "Lying Rear Lateral Raise",
              "href": "https://exrx.net/WeightExercises/DeltoidPosterior/LVLyingRearLateralRaiseH"
            },
            {
              "name": "Rear Delt Raise",
              "href": "https://exrx.net/WeightExercises/DeltoidPosterior/LVRearDeltRaise"
            },
            {
              "name": "Seated Rear Delt Row",
              "href": "https://exrx.net/WeightExercises/DeltoidPosterior/LVRearDeltRowHammer"
            },
            {
              "name": "Seated Rear Lateral Raise",
              "href": "https://exrx.net/WeightExercises/DeltoidPosterior/LVSeatedRearLateralRaise"
            },
            {
              "name": "T-Bar Rear Delt Row",
              "href": "https://exrx.net/WeightExercises/DeltoidPosterior/LVTBarRearDeltRow"
            }
          ],
          "Lever (selectorized)": [
            {
              "name": "Lying Rear Lateral Raise",
              "href": "https://exrx.net/WeightExercises/DeltoidPosterior/LVLyingRearLateralRaise"
            },
            { "name": "Rear Lateral Raise", "href": null },
            {
              "name": "Seated Rear Delt Row",
              "href": "https://exrx.net/WeightExercises/DeltoidPosterior/LVRearDeltRow"
            },
            {
              "name": "Seated Reverse Fly",
              "href": "https://exrx.net/WeightExercises/DeltoidPosterior/LVRearLateralRaise"
            }
          ],
          "Smith": [
            {
              "name": "Rear Delt Row",
              "href": "https://exrx.net/WeightExercises/DeltoidPosterior/SMRearDeltRow"
            }
          ],
          "Body Weight": [
            {
              "name": "Inverted Row",
              "href": "https://exrx.net/WeightExercises/DeltoidPosterior/BWRearDeltInvertedRow"
            }
          ],
          "Suspended": [
            {
              "name": "Rear Delt Row",
              "href": "https://exrx.net/WeightExercises/DeltoidPosterior/STRearDeltRow"
            },
            {
              "name": "Reverse Fly",
              "href": "https://exrx.net/WeightExercises/DeltoidPosterior/STReverseFly"
            }
          ],
          "Stretch": [
            {
              "name": "Fixed Bar",
              "href": "https://exrx.net/Stretches/DeltoidPosterior/FixedBar"
            },
            {
              "name": "Rear Deltoid",
              "href": "https://exrx.net/Stretches/DeltoidPosterior/RearDelt"
            }
          ]
        },
        "": {
          "Cable": [
            {
              "name": "Front Lateral Raise",
              "href": "https://exrx.net/WeightExercises/Supraspinatus/CBFrontLateralRaise"
            }
          ],
          " ": [],
          "Dumbbell": [
            {
              "name": "Lying Lateral Raise",
              "href": "https://exrx.net/WeightExercises/DeltoidLateral/DBLyingLateralRaise"
            }
          ]
        }
      }
    },
    {
      "name": "Upper Arms",
      "href": "https://exrx.net/Lists/ExList/ArmWt",
      "muscles": {
        "Triceps Brachii": {
          "Assisted": [
            {
              "name": "Triceps Dip",
              "href": "https://exrx.net/WeightExercises/Triceps/ASTriDip"
            }
          ],
          "Barbell": [
            {
              "name": "Close Grip Bench Press",
              "href": "https://exrx.net/WeightExercises/Triceps/BBCloseGripBenchPress"
            },
            {
              "name": "JM Press",
              "href": "https://exrx.net/WeightExercises/Triceps/BBJMPress"
            },
            {
              "name": "Lying Triceps Extension",
              "href": "https://exrx.net/WeightExercises/Triceps/BBLyingTriExt"
            },
            {
              "name": "Triceps Extension",
              "href": "https://exrx.net/WeightExercises/Triceps/BBTriExt"
            }
          ],
          "Cable": [
            {
              "name": "Bent-over Triceps Extension",
              "href": "https://exrx.net/WeightExercises/Triceps/CBBentoverTriExt"
            },
            {
              "name": "Forward Triceps Extension",
              "href": "https://exrx.net/WeightExercises/Triceps/CBForwardTricepsExt"
            },
            {
              "name": "Incline Triceps Extension",
              "href": "https://exrx.net/WeightExercises/Triceps/CBInclineTriExt"
            },
            {
              "name": "Kneeling Triceps Extension",
              "href": "https://exrx.net/WeightExercises/Triceps/CBKneelingTriExt"
            },
            {
              "name": "Lying Triceps Extension",
              "href": "https://exrx.net/WeightExercises/Triceps/CBLyingTriExt"
            },
            {
              "name": "Pushdown",
              "href": "https://exrx.net/WeightExercises/Triceps/CBPushdown"
            },
            {
              "name": "Side Triceps Extension",
              "href": "https://exrx.net/WeightExercises/Triceps/CBSideTricepsExt"
            },
            {
              "name": "Triceps Dip",
              "href": "https://exrx.net/WeightExercises/Triceps/CBTriDip"
            },
            {
              "name": "Triceps Extension",
              "href": "https://exrx.net/WeightExercises/Triceps/CBTriExt"
            }
          ],
          "Dumbbell": [
            {
              "name": "Kickback",
              "href": "https://exrx.net/WeightExercises/Triceps/DBKickback"
            },
            {
              "name": "Lying Triceps Extension",
              "href": "https://exrx.net/WeightExercises/Triceps/DBLyingTriExt"
            },
            {
              "name": "One Arm Triceps Extension",
              "href": "https://exrx.net/WeightExercises/Triceps/DBOneArmTriExt"
            },
            {
              "name": "Triceps Extension",
              "href": "https://exrx.net/WeightExercises/Triceps/DBTriExt"
            }
          ],
          "Lever (plate loaded)": [
            {
              "name": "Close Grip Bench Press",
              "href": "https://exrx.net/WeightExercises/Triceps/LVCloseGripBenchPressH"
            },
            {
              "name": "Triceps Extension",
              "href": "https://exrx.net/WeightExercises/Triceps/LVTriExtGripless"
            },
            {
              "name": "Triceps Dip",
              "href": "https://exrx.net/WeightExercises/Triceps/LVTriDipH"
            }
          ],
          "Lever (selectorized)": [
            {
              "name": "Incline Triceps Extension",
              "href": "https://exrx.net/WeightExercises/Triceps/LVInclineTricepsExtension"
            },
            {
              "name": "Overhead Triceps Extension",
              "href": "https://exrx.net/WeightExercises/Triceps/LVTricepsExtensionOH"
            },
            {
              "name": "Pushdown",
              "href": "https://exrx.net/WeightExercises/Triceps/LVPushdown"
            },
            { "name": "Seated Close Grip Press", "href": null },
            {
              "name": "Triceps Dip",
              "href": "https://exrx.net/WeightExercises/Triceps/LVTriDip"
            },
            {
              "name": "Triceps Extension",
              "href": "https://exrx.net/WeightExercises/Triceps/LVTriExt"
            }
          ],
          "Sled": [{ "name": "Standing Triceps Dip", "href": null }],
          "Smith": [
            {
              "name": "Close Grip Bench Press",
              "href": "https://exrx.net/WeightExercises/Triceps/SMCloseGripBenchPress"
            }
          ],
          "Weighted": [
            {
              "name": "Bench Dip",
              "href": "https://exrx.net/WeightExercises/Triceps/WtBenchDip"
            },
            {
              "name": "Close Grip Push-up",
              "href": "https://exrx.net/WeightExercises/Triceps/WtPushup"
            },
            {
              "name": "Triceps Dip",
              "href": "https://exrx.net/WeightExercises/Triceps/WtTriDip"
            }
          ],
          "Band-assisted": [{ "name": "Triceps Dip", "href": null }],
          "Body Weight": [
            {
              "name": "Bench Dip",
              "href": "https://exrx.net/WeightExercises/Triceps/BWBenchDip"
            },
            {
              "name": "Close Grip Push-up",
              "href": "https://exrx.net/WeightExercises/Triceps/BWCloseGripPushup"
            },
            {
              "name": "Suspended Triceps Extension",
              "href": "https://exrx.net/WeightExercises/Triceps/BWSuspendedTricepsExtension"
            },
            {
              "name": "Triceps Dip",
              "href": "https://exrx.net/WeightExercises/Triceps/BWTriDip"
            }
          ],
          "Suspended": [
            {
              "name": "Triceps Dip",
              "href": "https://exrx.net/WeightExercises/Triceps/STTriDip"
            },
            {
              "name": "Triceps Extension",
              "href": "https://exrx.net/WeightExercises/Triceps/STTricepsExtension"
            }
          ],
          "Self-assisted": [
            {
              "name": "Triceps Dip",
              "href": "https://exrx.net/WeightExercises/Triceps/ASTricepsDipSelf"
            }
          ],
          "Stretch": [
            {
              "name": "Overhead",
              "href": "https://exrx.net/Stretches/Triceps/Overhead"
            },
            {
              "name": "PNF",
              "href": "https://exrx.net/Stretches/Triceps/PNFOverhead"
            },
            {
              "name": "Towel",
              "href": "https://exrx.net/Stretches/Triceps/Towel"
            }
          ]
        },
        "Biceps Brachii": {
          "Barbell": [
            {
              "name": "Curl",
              "href": "https://exrx.net/WeightExercises/Biceps/BBCurl"
            },
            {
              "name": "Drag Curl",
              "href": "https://exrx.net/WeightExercises/Biceps/BBDragCurl"
            }
          ],
          "Cable": [
            {
              "name": "Alternating Curl",
              "href": "https://exrx.net/WeightExercises/Biceps/CBAlternatingCurl"
            },
            {
              "name": "Curl",
              "href": "https://exrx.net/WeightExercises/Biceps/CBCurl"
            },
            { "name": "Supine Curl", "href": null }
          ],
          "Dumbbell": [
            { "name": "Curl", "href": null },
            {
              "name": "Incline Curl",
              "href": "https://exrx.net/WeightExercises/Biceps/DBInclineCurl"
            }
          ],
          "Lever (selectorized)": [
            {
              "name": "Curl",
              "href": "https://exrx.net/WeightExercises/Biceps/LVCurl"
            }
          ],
          "Body Weight": [
            {
              "name": "Chin-up",
              "href": "https://exrx.net/WeightExercises/LatissimusDorsi/BWUnderhandChinup"
            },
            {
              "name": "Underhand Inverted Row",
              "href": "https://exrx.net/WeightExercises/BackGeneral/BWUnderhandSupineRow"
            }
          ]
        },
        "Brachialis": {
          "Barbell": [
            {
              "name": "Preacher Curl",
              "href": "https://exrx.net/WeightExercises/Brachialis/BBPreacherCurl"
            },
            {
              "name": "Prone Incline Curl",
              "href": "https://exrx.net/WeightExercises/Brachialis/BBProneInclineCurl"
            }
          ],
          "Cable": [
            {
              "name": "Concentration Curl",
              "href": "https://exrx.net/WeightExercises/Brachialis/CBConcentrationCurl"
            },
            {
              "name": "Preacher Curl",
              "href": "https://exrx.net/WeightExercises/Brachialis/CBPreacherCurl"
            },
            {
              "name": "Prone Incline Curl",
              "href": "https://exrx.net/WeightExercises/Brachialis/CBProneInclineCurl"
            }
          ],
          "Dumbbell": [
            {
              "name": "Concentration Curl",
              "href": "https://exrx.net/WeightExercises/Brachialis/DBConcentrationCurl"
            },
            {
              "name": "Preacher Curl",
              "href": "https://exrx.net/WeightExercises/Brachialis/DBPreacherCurl"
            },
            {
              "name": "Prone Incline Curl",
              "href": "https://exrx.net/WeightExercises/Brachialis/DBProneInclineCurl"
            }
          ],
          "Lever (plate loaded)": [
            {
              "name": "Preacher Curl",
              "href": "https://exrx.net/WeightExercises/Brachialis/LVPreacherCurlH"
            }
          ],
          "Lever (selectorized)": [
            {
              "name": "Preacher Curl",
              "href": "https://exrx.net/WeightExercises/Brachialis/LVPreacherCurl"
            }
          ],
          "Suspended": [
            {
              "name": "Arm Curl",
              "href": "https://exrx.net/WeightExercises/Brachialis/STArmCurl"
            }
          ]
        }
      }
    },
    {
      "name": "Forearms",
      "href": "https://exrx.net/Lists/ExList/ForeArmWt",
      "muscles": {
        "Brachioradialis": {
          "Barbell": [
            {
              "name": "Reverse Curl",
              "href": "https://exrx.net/WeightExercises/Brachioradialis/BBReverseCurl"
            },
            {
              "name": "Reverse Preacher Curl",
              "href": "https://exrx.net/WeightExercises/Brachioradialis/BBReversePreacherCurl"
            }
          ],
          "Cable": [
            {
              "name": "Hammer Curl",
              "href": "https://exrx.net/WeightExercises/Brachioradialis/CBHammerCurl"
            },
            {
              "name": "Reverse Curl",
              "href": "https://exrx.net/WeightExercises/Brachioradialis/CBReverseCurl"
            },
            { "name": "Reverse Preacher Curl", "href": null }
          ],
          "Dumbbell": [
            {
              "name": "Hammer Curl",
              "href": "https://exrx.net/WeightExercises/Brachioradialis/DBHammerCurl"
            }
          ],
          "Lever (selectorized)": [
            {
              "name": "Hammer Preacher Curl",
              "href": "https://exrx.net/WeightExercises/Brachioradialis/LVHammerPreacherCurl"
            },
            {
              "name": "Reverse Curl",
              "href": "https://exrx.net/WeightExercises/Brachioradialis/LVReverseCurl"
            },
            {
              "name": "Reverse Preacher Curl",
              "href": "https://exrx.net/WeightExercises/Brachioradialis/LVReversePreacherCurl"
            }
          ],
          "Stretch": [
            {
              "name": "Standing",
              "href": "https://exrx.net/Stretches/Brachioradialis/Standing"
            }
          ]
        },
        "Wrist Flexors": {
          "Barbell": [
            {
              "name": "Wrist Curl",
              "href": "https://exrx.net/WeightExercises/WristFlexors/BBWristCurl"
            }
          ],
          "Cable": [
            {
              "name": "Wrist Curl",
              "href": "https://exrx.net/WeightExercises/WristFlexors/CBWristCurl"
            },
            {
              "name": "Wrist Roller",
              "href": "https://exrx.net/WeightExercises/WristFlexors/CBRollerWristFlexion"
            }
          ],
          "Dumbbell": [
            {
              "name": "Wrist Curl",
              "href": "https://exrx.net/WeightExercises/WristFlexors/DBWristCurl"
            },
            {
              "name": "Ulnar Deviation",
              "href": "https://exrx.net/WeightExercises/WristFlexors/DBUlnarFlexion"
            }
          ],
          "Lever (plate loaded)": [
            {
              "name": "Grip",
              "href": "https://exrx.net/WeightExercises/WristFlexors/LVGripPL"
            },
            {
              "name": "Wrist Curl",
              "href": "https://exrx.net/WeightExercises/WristFlexors/LVWristCurlPL"
            }
          ],
          "Lever (selectorized)": [
            {
              "name": "Grip",
              "href": "https://exrx.net/WeightExercises/WristFlexors/LVGrip"
            },
            {
              "name": "Ulnar Deviation",
              "href": "https://exrx.net/WeightExercises/WristFlexors/LVUlnarFlexion"
            },
            {
              "name": "Wrist Curl",
              "href": "https://exrx.net/WeightExercises/WristFlexors/LVWristCurl"
            },
            {
              "name": "Wrist Roller",
              "href": "https://exrx.net/WeightExercises/WristFlexors/LVRollerWristFlexion"
            }
          ],
          "Sled (selectorized)": [
            {
              "name": "One Hand Grip",
              "href": "https://exrx.net/WeightExercises/WristFlexors/SLGrip"
            }
          ],
          "Sled (plate loaded)": [
            {
              "name": "Grip (plate loaded)",
              "href": "https://exrx.net/WeightExercises/WristFlexors/SLGripPlateLoaded"
            },
            {
              "name": "One Hand",
              "href": "https://exrx.net/WeightExercises/WristFlexors/SLOneHandGripPlateLoaded"
            },
            {
              "name": "One Hand Pinch Grip",
              "href": "https://exrx.net/WeightExercises/WristFlexors/SLOneHandPinchGripPL"
            }
          ],
          "Stretch": [
            {
              "name": "Praying",
              "href": "https://exrx.net/Stretches/WristFlexors/Praying"
            },
            {
              "name": "Seated",
              "href": "https://exrx.net/Stretches/WristFlexors/Seated"
            },
            {
              "name": "Single Arm",
              "href": "https://exrx.net/Stretches/WristFlexors/Single"
            },
            {
              "name": "Kneeling",
              "href": "https://exrx.net/Stretches/WristFlexors/Kneeling"
            }
          ]
        },
        "Wrist Extensors": {
          "Barbell": [
            {
              "name": "Reverse Wrist Curl",
              "href": "https://exrx.net/WeightExercises/WristExtensors/BBReverseWristCurl"
            }
          ],
          "Cable": [
            {
              "name": "Reverse Wrist Curl",
              "href": "https://exrx.net/WeightExercises/WristExtensors/CBReverseWristCurl"
            },
            {
              "name": "Wrist Roller",
              "href": "https://exrx.net/WeightExercises/WristExtensors/CBRollerWristExtention"
            }
          ],
          "Dumbbell": [
            {
              "name": "Radial Deviation",
              "href": "https://exrx.net/WeightExercises/WristExtensors/DBRadialFlexion"
            },
            {
              "name": "Reverse Wrist Curl",
              "href": "https://exrx.net/WeightExercises/WristExtensors/DBReverseWristCurl"
            }
          ],
          "Lever (plate loaded)": [
            {
              "name": "Reverse Wrist Curl",
              "href": "https://exrx.net/WeightExercises/WristExtensors/LVReverseWristCurlPL"
            }
          ],
          "Lever (selectorized)": [
            {
              "name": "Radial Deviation",
              "href": "https://exrx.net/WeightExercises/WristExtensors/LVRadialFlexion"
            },
            {
              "name": "Reverse Wrist Curl",
              "href": "https://exrx.net/WeightExercises/WristExtensors/LVReverseWristCurl"
            },
            {
              "name": "Wrist Roller",
              "href": "https://exrx.net/WeightExercises/WristExtensors/LVRollerWristExtention"
            }
          ],
          "Stretch": [
            {
              "name": "Kneeling",
              "href": "https://exrx.net/Stretches/WristExtensors/Kneeling"
            },
            {
              "name": "Single Arm",
              "href": "https://exrx.net/Stretches/WristExtensors/Single"
            }
          ]
        },
        "Pronators": {
          "Dumbbell": [
            {
              "name": "Lying Pronation",
              "href": "https://exrx.net/WeightExercises/Pronators/DBLyingPronationUp"
            },
            {
              "name": "Seated Pronation",
              "href": "https://exrx.net/WeightExercises/Pronators/DBSeatedPronation"
            }
          ],
          "Lever (selectorized)": [
            {
              "name": "Seated Pronation",
              "href": "https://exrx.net/WeightExercises/Pronators/LVSeatedPronation"
            },
            {
              "name": "Standing Pronation",
              "href": "https://exrx.net/WeightExercises/Pronators/LVPronation"
            }
          ]
        },
        "Supinators": {
          "Dumbbell": [
            {
              "name": "Lying Supination",
              "href": "https://exrx.net/WeightExercises/Supinators/DBLyingSupinationUp"
            },
            {
              "name": "Seated Supination",
              "href": "https://exrx.net/WeightExercises/Supinators/DBSeatedSupination"
            }
          ],
          "Lever (selectorized)": [
            {
              "name": "Seated Supination",
              "href": "https://exrx.net/WeightExercises/Supinators/LVSeatedSupination"
            },
            {
              "name": "Standing Supination",
              "href": "https://exrx.net/WeightExercises/Supinators/LVSupination"
            }
          ]
        }
      }
    }
  ]
}
